README.rst
setup.py
shadowhack/__init__.py
shadowhack/shadow_hack.py
shadowhack.egg-info/PKG-INFO
shadowhack.egg-info/SOURCES.txt
shadowhack.egg-info/dependency_links.txt
shadowhack.egg-info/not-zip-safe
shadowhack.egg-info/top_level.txt