Metadata-Version: 1.1
Name: shadowhack
Version: 0.1
Summary: The ShadowHack
Home-page: http://github.com/gitrahul9/shadowhack
Author: shadowhack
Author-email: rahulsingal2009@gmail.com
License: MIT
Keywords: shadowhack
Platform: UNKNOWN
Classifier: Development Status :: 4 - Beta
Classifier: License :: OSI Approved :: MIT License
Classifier: Programming Language :: Python :: 2.7
